dicom_helper/__init__.py
dicom_helper/class_codes.py
dicom_helper/class_colors.py
dicom_helper/dicom_conversion.py
dicom_helper/main.py
dicom_helper/parser.py
dicom_helper/utils.py
mrsegmentator/__init__.py
mrsegmentator/config.py
mrsegmentator/custom_logger.py
mrsegmentator/inference.py
mrsegmentator/main.py
mrsegmentator/parser.py
mrsegmentator/simpleitk_reader_writer.py
mrsegmentator/utils.py
mrsegmentator-1.3.1.dist-info/licenses/License.txt
mrsegmentator-1.3.1.dist-info/METADATA
mrsegmentator-1.3.1.dist-info/WHEEL
mrsegmentator-1.3.1.dist-info/entry_points.txt
mrsegmentator-1.3.1.dist-info/top_level.txt
mrsegmentator-1.3.1.dist-info/RECORD
