Metadata-Version: 2.4
Name: mrsegmentator
Version: 1.3.1
Summary: Multi-Modality Segmentation of 40 Classes in MRI and CT
Home-page: https://github.com/hhaentze/mrsegmentator
Author: Hartmut Häntze
Author-email: hartmut.haentze@charite.de
Project-URL: Bug Tracker, https://github.com/hhaentze/mrsegmentator/issues
Project-URL: repository, https://github.com/hhaentze/mrsegmentator
Classifier: Programming Language :: Python :: 3
Classifier: License :: OSI Approved :: Apache Software License
Classifier: Operating System :: POSIX :: Linux
Classifier: Intended Audience :: Developers
Classifier: Intended Audience :: Science/Research
Classifier: Intended Audience :: Healthcare Industry
Classifier: Topic :: Scientific/Engineering :: Artificial Intelligence
Classifier: Topic :: Scientific/Engineering :: Image Recognition
Classifier: Topic :: Scientific/Engineering :: Medical Science Apps.
Requires-Python: <3.13,>=3.9
License-File: License.txt
Requires-Dist: torch<=2.3.1
Requires-Dist: nnunetv2==2.2.1
Requires-Dist: argparse==1.4.0
Requires-Dist: numpy<2
Requires-Dist: pydicom
Requires-Dist: highdicom
Provides-Extra: dev
Requires-Dist: black; extra == "dev"
Requires-Dist: flake8-nb; extra == "dev"
Requires-Dist: isort; extra == "dev"
Requires-Dist: mypy; extra == "dev"
Dynamic: license-file
